{
  "timestamp": "2026-01-12T17:14:16.774Z",
  "totalAccounts": 3,
  "successful": 0,
  "failed": 3,
  "outOfStock": 0,
  "limitReached": 0,
  "results": [
    {
      "index": 0,
      "username": "*****ar11",
      "status": "error",
      "message": "Sign in failed",
      "timestamp": "2026-01-12T17:13:42.709Z"
    },
    {
      "index": 1,
      "username": "****uuzo",
      "status": "error",
      "message": "Sign in failed",
      "timestamp": "2026-01-12T17:13:59.575Z"
    },
    {
      "index": 2,
      "username": "********eryl",
      "status": "error",
      "message": "Sign in failed",
      "timestamp": "2026-01-12T17:14:16.412Z"
    }
  ]
}